{
	"configurations" : 
	[
		{
			"directories" : 
			[
				{
					"build" : ".",
					"jsonFile" : "directory-.-Debug-f5ebdc15457944623624.json",
					"minimumCMakeVersion" : 
					{
						"string" : "2.8.12"
					},
					"projectIndex" : 0,
					"source" : ".",
					"targetIndexes" : 
					[
						0,
						1,
						2,
						3,
						4,
						5,
						6,
						7
					]
				}
			],
			"name" : "Debug",
			"projects" : 
			[
				{
					"directoryIndexes" : 
					[
						0
					],
					"name" : "Thermo-Elastic",
					"targetIndexes" : 
					[
						0,
						1,
						2,
						3,
						4,
						5,
						6,
						7
					]
				}
			],
			"targets" : 
			[
				{
					"directoryIndex" : 0,
					"id" : "Thermo-Elastic::@6890427a1f51a3e7e1df",
					"jsonFile" : "target-Thermo-Elastic-Debug-e0cf33ef9c5787e8be73.json",
					"name" : "Thermo-Elastic",
					"projectIndex" : 0
				},
				{
					"directoryIndex" : 0,
					"id" : "debug::@6890427a1f51a3e7e1df",
					"jsonFile" : "target-debug-Debug-b5206c4ee7273acb89ef.json",
					"name" : "debug",
					"projectIndex" : 0
				},
				{
					"directoryIndex" : 0,
					"id" : "distclean::@6890427a1f51a3e7e1df",
					"jsonFile" : "target-distclean-Debug-c42726cb78be9b454116.json",
					"name" : "distclean",
					"projectIndex" : 0
				},
				{
					"directoryIndex" : 0,
					"id" : "info::@6890427a1f51a3e7e1df",
					"jsonFile" : "target-info-Debug-b4bc69433a9e2a269247.json",
					"name" : "info",
					"projectIndex" : 0
				},
				{
					"directoryIndex" : 0,
					"id" : "release::@6890427a1f51a3e7e1df",
					"jsonFile" : "target-release-Debug-e6e9258604a00e1d0feb.json",
					"name" : "release",
					"projectIndex" : 0
				},
				{
					"directoryIndex" : 0,
					"id" : "run::@6890427a1f51a3e7e1df",
					"jsonFile" : "target-run-Debug-951c3af3afe626425a9b.json",
					"name" : "run",
					"projectIndex" : 0
				},
				{
					"directoryIndex" : 0,
					"id" : "runclean::@6890427a1f51a3e7e1df",
					"jsonFile" : "target-runclean-Debug-2f7e8ec1153fc5acf9df.json",
					"name" : "runclean",
					"projectIndex" : 0
				},
				{
					"directoryIndex" : 0,
					"id" : "strip_comments::@6890427a1f51a3e7e1df",
					"jsonFile" : "target-strip_comments-Debug-fb4f8c95b0c8f36e4dab.json",
					"name" : "strip_comments",
					"projectIndex" : 0
				}
			]
		}
	],
	"kind" : "codemodel",
	"paths" : 
	{
		"build" : "/home/ubuntu/CLionProjects/Thermo-Elastic/cmake-build-debug",
		"source" : "/home/ubuntu/CLionProjects/Thermo-Elastic"
	},
	"version" : 
	{
		"major" : 2,
		"minor" : 3
	}
}
